MANIFEST.in
README.txt
setup.py
src/busyflow/__init__.py
src/busyflow.pivotal.egg-info/PKG-INFO
src/busyflow.pivotal.egg-info/SOURCES.txt
src/busyflow.pivotal.egg-info/dependency_links.txt
src/busyflow.pivotal.egg-info/namespace_packages.txt
src/busyflow.pivotal.egg-info/not-zip-safe
src/busyflow.pivotal.egg-info/requires.txt
src/busyflow.pivotal.egg-info/top_level.txt
src/busyflow/pivotal/__init__.py
src/busyflow/pivotal/tests.py
src/busyflow/pivotal/tzmap.txt