Metadata-Version: 1.0
Name: busyflow.pivotal
Version: 0.1.10
Summary: Pivotal API client library.
Home-page: http://github.com/Ignas/busyflow.pivotal/
Author: Ignas Mikalajunas
Author-email: ignas@nous.lt
License: GPL
Platform: UNKNOWN
Classifier: Development Status :: 4 - Beta
Classifier: Environment :: Web Environment
Classifier: Intended Audience :: Developers
Classifier: License :: OSI Approved :: GNU General Public License (GPL)
Classifier: Operating System :: OS Independent
Classifier: Programming Language :: Python
Classifier: Topic :: Internet :: WWW/HTTP
